[
  {
    "date": "19/06/25",
    "day": "",
    "time": "",
    "status": "FT",
    "group": "H2H",
    "title": "Morris Elite 2-2 Westchester Flames",
    "homeTeam": "Morris Elite",
    "awayTeam": "Westchester Flames",
    "score": "2-2",
    "matchId": "4846071",
    "targetMatchId": "5042296",
    "goals": [
      "",
      "22' 0-1<br>24' 1-1",
      "",
      "",
      "",
      "62' 2-1<br>74' 2-2",
      "",
      ""
    ],
    "isReference": true
  },
  {
    "date": "18/05/25",
    "day": "",
    "time": "",
    "status": "FT",
    "group": "H2H",
    "title": "Westchester Flames 1-0 Morris Elite",
    "homeTeam": "Westchester Flames",
    "awayTeam": "Morris Elite",
    "score": "1-0",
    "matchId": "4846037",
    "targetMatchId": "5042296",
    "goals": [
      "",
      "",
      "",
      "",
      "",
      "",
      "",
      ""
    ],
    "isReference": true
  },
  {
    "date": "02/06/24",
    "day": "",
    "time": "",
    "status": "FT",
    "group": "H2H",
    "title": "Westchester Flames 2-1 Morris Elite",
    "homeTeam": "Westchester Flames",
    "awayTeam": "Morris Elite",
    "score": "2-1",
    "matchId": "4679471",
    "targetMatchId": "5042296",
    "goals": [
      "",
      "",
      "",
      "",
      "60' 1-0",
      "73' 1-1<br>75' 2-1",
      "",
      ""
    ],
    "isReference": true
  },
  {
    "date": "28/05/23",
    "day": "",
    "time": "",
    "status": "FT",
    "group": "H2H",
    "title": "Westchester Flames 1-2 Morris Elite",
    "homeTeam": "Westchester Flames",
    "awayTeam": "Morris Elite",
    "score": "1-2",
    "matchId": "4491286",
    "targetMatchId": "5042296",
    "goals": [
      "7' 1-0",
      "",
      "",
      "",
      "",
      "",
      "90' 1-1",
      "90+6' 1-2"
    ],
    "isReference": true
  },
  {
    "date": "15/05/22",
    "day": "",
    "time": "",
    "status": "FT",
    "group": "H2H",
    "title": "Westchester Flames 3-0 Morris Elite",
    "homeTeam": "Westchester Flames",
    "awayTeam": "Morris Elite",
    "score": "3-0",
    "matchId": "4312476",
    "targetMatchId": "5042296",
    "goals": [
      "",
      "",
      "",
      "",
      "",
      "",
      "",
      ""
    ],
    "isReference": true
  },
  {
    "date": "04/07/21",
    "day": "",
    "time": "",
    "status": "FT",
    "group": "H2H",
    "title": "Morris Elite 1-1 Westchester Flames",
    "homeTeam": "Morris Elite",
    "awayTeam": "Westchester Flames",
    "score": "1-1",
    "matchId": "4176763",
    "targetMatchId": "5042296",
    "goals": [
      "",
      "",
      "",
      "",
      "",
      "",
      "",
      ""
    ],
    "isReference": true
  },
  {
    "date": "14/06/21",
    "day": "",
    "time": "",
    "status": "FT",
    "group": "H2H",
    "title": "Westchester Flames 1-3 Morris Elite",
    "homeTeam": "Westchester Flames",
    "awayTeam": "Morris Elite",
    "score": "1-3",
    "matchId": "4162558",
    "targetMatchId": "5042296",
    "goals": [
      "",
      "",
      "",
      "",
      "",
      "",
      "",
      ""
    ],
    "isReference": true
  },
  {
    "date": "03/07/26",
    "day": "",
    "time": "",
    "status": "FT",
    "group": "Morris Elite Hist",
    "title": "FC Motown II 8-0 Morris Elite",
    "homeTeam": "FC Motown II",
    "awayTeam": "Morris Elite",
    "score": "8-0",
    "matchId": "5042142",
    "targetMatchId": "5042296",
    "goals": [
      "13' 1-0",
      "22' 2-0",
      "",
      "",
      "60' 3-0",
      "64' 4-0<br>74' 5-0",
      "81' 6-0<br>86' 7-0<br>88' 8-0",
      ""
    ],
    "isReference": true
  },
  {
    "date": "28/06/26",
    "day": "",
    "time": "",
    "status": "FT",
    "group": "Morris Elite Hist",
    "title": "Hudson Valley Hammers 4-3 Morris Elite",
    "homeTeam": "Hudson Valley Hammers",
    "awayTeam": "Morris Elite",
    "score": "4-3",
    "matchId": "5042020",
    "targetMatchId": "5042296",
    "goals": [
      "",
      "",
      "",
      "",
      "",
      "",
      "",
      ""
    ],
    "isReference": true
  },
  {
    "date": "25/06/26",
    "day": "",
    "time": "",
    "status": "FT",
    "group": "Morris Elite Hist",
    "title": "Morris Elite 2-0 New Jersey Copa",
    "homeTeam": "Morris Elite",
    "awayTeam": "New Jersey Copa",
    "score": "2-0",
    "matchId": "5041949",
    "targetMatchId": "5042296",
    "goals": [
      "",
      "",
      "",
      "",
      "54' 1-0<br>58' 2-0",
      "",
      "",
      ""
    ],
    "isReference": true
  },
  {
    "date": "21/06/26",
    "day": "",
    "time": "",
    "status": "FT",
    "group": "Morris Elite Hist",
    "title": "Cedar Stars Rush 2-0 Morris Elite",
    "homeTeam": "Cedar Stars Rush",
    "awayTeam": "Morris Elite",
    "score": "2-0",
    "matchId": "5041796",
    "targetMatchId": "5042296",
    "goals": [
      "",
      "",
      "",
      "",
      "",
      "",
      "",
      ""
    ],
    "isReference": true
  },
  {
    "date": "11/06/26",
    "day": "",
    "time": "",
    "status": "FT",
    "group": "Morris Elite Hist",
    "title": "Manhattan SC 5-1 Morris Elite",
    "homeTeam": "Manhattan SC",
    "awayTeam": "Morris Elite",
    "score": "5-1",
    "matchId": "5040591",
    "targetMatchId": "5042296",
    "goals": [
      "",
      "",
      "",
      "",
      "",
      "",
      "",
      ""
    ],
    "isReference": true
  },
  {
    "date": "08/06/26",
    "day": "",
    "time": "",
    "status": "FT",
    "group": "Morris Elite Hist",
    "title": "Long Island Rough Riders 2-1 Morris Elite",
    "homeTeam": "Long Island Rough Riders",
    "awayTeam": "Morris Elite",
    "score": "2-1",
    "matchId": "5040470",
    "targetMatchId": "5042296",
    "goals": [
      "",
      "",
      "",
      "",
      "",
      "",
      "",
      ""
    ],
    "isReference": true
  },
  {
    "date": "04/06/26",
    "day": "",
    "time": "",
    "status": "FT",
    "group": "Morris Elite Hist",
    "title": "Morris Elite 0-4 FC Motown II",
    "homeTeam": "Morris Elite",
    "awayTeam": "FC Motown II",
    "score": "0-4",
    "matchId": "5040574",
    "targetMatchId": "5042296",
    "goals": [
      "",
      "23' 0-1",
      "45' 0-2",
      "",
      "49' 0-3",
      "63' 0-4",
      "",
      ""
    ],
    "isReference": true
  },
  {
    "date": "31/05/26",
    "day": "",
    "time": "",
    "status": "FT",
    "group": "Morris Elite Hist",
    "title": "Morris Elite 0-4 Manhattan SC",
    "homeTeam": "Morris Elite",
    "awayTeam": "Manhattan SC",
    "score": "0-4",
    "matchId": "5040384",
    "targetMatchId": "5042296",
    "goals": [
      "",
      "",
      "",
      "",
      "",
      "69' 0-1<br>71' 0-2",
      "85' 0-3<br>88' 0-4",
      ""
    ],
    "isReference": true
  },
  {
    "date": "24/05/26",
    "day": "",
    "time": "",
    "status": "FT",
    "group": "Morris Elite Hist",
    "title": "Morris Elite 2-1 Hudson Valley Hammers",
    "homeTeam": "Morris Elite",
    "awayTeam": "Hudson Valley Hammers",
    "score": "2-1",
    "matchId": "5040093",
    "targetMatchId": "5042296",
    "goals": [
      "",
      "",
      "",
      "",
      "",
      "",
      "",
      ""
    ],
    "isReference": true
  },
  {
    "date": "21/05/26",
    "day": "",
    "time": "",
    "status": "FT",
    "group": "Morris Elite Hist",
    "title": "Morris Elite 0-2 Ironbound SC",
    "homeTeam": "Morris Elite",
    "awayTeam": "Ironbound SC",
    "score": "0-2",
    "matchId": "5040291",
    "targetMatchId": "5042296",
    "goals": [
      "",
      "",
      "34' 0-1",
      "",
      "",
      "",
      "",
      "90+3' 0-2"
    ],
    "isReference": true
  },
  {
    "date": "13/07/25",
    "day": "",
    "time": "",
    "status": "FT",
    "group": "Morris Elite Hist",
    "title": "Morris Elite 1-1 Hudson Valley Hammers",
    "homeTeam": "Morris Elite",
    "awayTeam": "Hudson Valley Hammers",
    "score": "1-1",
    "matchId": "4845995",
    "targetMatchId": "5042296",
    "goals": [
      "13' 0-1",
      "",
      "",
      "",
      "",
      "",
      "84' 1-1",
      ""
    ],
    "isReference": true
  },
  {
    "date": "10/07/25",
    "day": "",
    "time": "",
    "status": "FT",
    "group": "Morris Elite Hist",
    "title": "New Jersey Copa 0-1 Morris Elite",
    "homeTeam": "New Jersey Copa",
    "awayTeam": "Morris Elite",
    "score": "0-1",
    "matchId": "4845942",
    "targetMatchId": "5042296",
    "goals": [
      "",
      "",
      "",
      "",
      "",
      "",
      "",
      ""
    ],
    "isReference": true
  },
  {
    "date": "06/07/25",
    "day": "",
    "time": "",
    "status": "FT",
    "group": "Morris Elite Hist",
    "title": "Manhattan SC 3-4 Morris Elite",
    "homeTeam": "Manhattan SC",
    "awayTeam": "Morris Elite",
    "score": "3-4",
    "matchId": "4845896",
    "targetMatchId": "5042296",
    "goals": [
      "",
      "19' 0-1<br>20' 0-2",
      "43' 1-2",
      "",
      "46' 2-2",
      "62' 2-3",
      "76' 3-3<br>87' 3-4",
      ""
    ],
    "isReference": true
  },
  {
    "date": "03/07/25",
    "day": "",
    "time": "",
    "status": "FT",
    "group": "Morris Elite Hist",
    "title": "Ironbound SC 0-1 Morris Elite",
    "homeTeam": "Ironbound SC",
    "awayTeam": "Morris Elite",
    "score": "0-1",
    "matchId": "4845868",
    "targetMatchId": "5042296",
    "goals": [
      "",
      "",
      "",
      "",
      "",
      "",
      "85' 0-1",
      ""
    ],
    "isReference": true
  },
  {
    "date": "29/06/25",
    "day": "",
    "time": "",
    "status": "FT",
    "group": "Morris Elite Hist",
    "title": "Morris Elite 0-2 Cedar Stars Rush",
    "homeTeam": "Morris Elite",
    "awayTeam": "Cedar Stars Rush",
    "score": "0-2",
    "matchId": "4845802",
    "targetMatchId": "5042296",
    "goals": [
      "7' 0-1",
      "",
      "",
      "",
      "",
      "",
      "90' 0-2",
      ""
    ],
    "isReference": true
  },
  {
    "date": "26/06/25",
    "day": "",
    "time": "",
    "status": "FT",
    "group": "Morris Elite Hist",
    "title": "Morris Elite 1-4 FC Motown II",
    "homeTeam": "Morris Elite",
    "awayTeam": "FC Motown II",
    "score": "1-4",
    "matchId": "4845769",
    "targetMatchId": "5042296",
    "goals": [
      "",
      "",
      "",
      "",
      "",
      "",
      "",
      ""
    ],
    "isReference": true
  },
  {
    "date": "19/06/25",
    "day": "",
    "time": "",
    "status": "FT",
    "group": "Morris Elite Hist",
    "title": "Morris Elite 2-2 Westchester Flames",
    "homeTeam": "Morris Elite",
    "awayTeam": "Westchester Flames",
    "score": "2-2",
    "matchId": "4846071",
    "targetMatchId": "5042296",
    "goals": [
      "",
      "22' 0-1<br>24' 1-1",
      "",
      "",
      "",
      "62' 2-1<br>74' 2-2",
      "",
      ""
    ],
    "isReference": true
  },
  {
    "date": "15/06/25",
    "day": "",
    "time": "",
    "status": "FT",
    "group": "Morris Elite Hist",
    "title": "Morris Elite 1-3 Long Island Rough Riders",
    "homeTeam": "Morris Elite",
    "awayTeam": "Long Island Rough Riders",
    "score": "1-3",
    "matchId": "4845589",
    "targetMatchId": "5042296",
    "goals": [
      "",
      "",
      "35' 0-1",
      "",
      "",
      "65' 0-2<br>68' 0-3<br>75' 1-3",
      "",
      ""
    ],
    "isReference": true
  },
  {
    "date": "08/06/25",
    "day": "",
    "time": "",
    "status": "FT",
    "group": "Morris Elite Hist",
    "title": "Morris Elite 2-1 Staten Island ASC",
    "homeTeam": "Morris Elite",
    "awayTeam": "Staten Island ASC",
    "score": "2-1",
    "matchId": "4845481",
    "targetMatchId": "5042296",
    "goals": [
      "",
      "",
      "",
      "",
      "",
      "",
      "",
      ""
    ],
    "isReference": true
  },
  {
    "date": "02/06/25",
    "day": "",
    "time": "",
    "status": "FT",
    "group": "Morris Elite Hist",
    "title": "Long Island Rough Riders 2-0 Morris Elite",
    "homeTeam": "Long Island Rough Riders",
    "awayTeam": "Morris Elite",
    "score": "2-0",
    "matchId": "4845408",
    "targetMatchId": "5042296",
    "goals": [
      "",
      "",
      "32' 1-0",
      "",
      "",
      "",
      "90' 2-0",
      ""
    ],
    "isReference": true
  },
  {
    "date": "28/06/26",
    "day": "",
    "time": "",
    "status": "FT",
    "group": "Westchester Flames Hist",
    "title": "Westchester Flames 0-1 Cedar Stars Rush",
    "homeTeam": "Westchester Flames",
    "awayTeam": "Cedar Stars Rush",
    "score": "0-1",
    "matchId": "5042022",
    "targetMatchId": "5042296",
    "goals": [
      "",
      "25' 0-1",
      "",
      "",
      "",
      "",
      "",
      ""
    ],
    "isReference": true
  },
  {
    "date": "25/06/26",
    "day": "",
    "time": "",
    "status": "FT",
    "group": "Westchester Flames Hist",
    "title": "Westchester Flames 0-3 Hudson Valley Hammers",
    "homeTeam": "Westchester Flames",
    "awayTeam": "Hudson Valley Hammers",
    "score": "0-3",
    "matchId": "5041953",
    "targetMatchId": "5042296",
    "goals": [
      "2' 0-1",
      "18' 0-2",
      "",
      "",
      "48' 0-3",
      "",
      "",
      ""
    ],
    "isReference": true
  },
  {
    "date": "22/06/26",
    "day": "",
    "time": "",
    "status": "FT",
    "group": "Westchester Flames Hist",
    "title": "Long Island Rough Riders 4-0 Westchester Flames",
    "homeTeam": "Long Island Rough Riders",
    "awayTeam": "Westchester Flames",
    "score": "4-0",
    "matchId": "5041835",
    "targetMatchId": "5042296",
    "goals": [
      "",
      "",
      "",
      "",
      "",
      "",
      "",
      ""
    ],
    "isReference": true
  },
  {
    "date": "18/06/26",
    "day": "",
    "time": "",
    "status": "FT",
    "group": "Westchester Flames Hist",
    "title": "Westchester Flames 3-3 Ironbound SC",
    "homeTeam": "Westchester Flames",
    "awayTeam": "Ironbound SC",
    "score": "3-3",
    "matchId": "5040695",
    "targetMatchId": "5042296",
    "goals": [
      "",
      "",
      "",
      "",
      "",
      "",
      "",
      ""
    ],
    "isReference": true
  },
  {
    "date": "14/06/26",
    "day": "",
    "time": "",
    "status": "FT",
    "group": "Westchester Flames Hist",
    "title": "Westchester Flames 5-0 Manhattan SC",
    "homeTeam": "Westchester Flames",
    "awayTeam": "Manhattan SC",
    "score": "5-0",
    "matchId": "5040718",
    "targetMatchId": "5042296",
    "goals": [
      "",
      "",
      "",
      "",
      "",
      "",
      "",
      ""
    ],
    "isReference": true
  },
  {
    "date": "11/06/26",
    "day": "",
    "time": "",
    "status": "FT",
    "group": "Westchester Flames Hist",
    "title": "Cedar Stars Rush 2-0 Westchester Flames",
    "homeTeam": "Cedar Stars Rush",
    "awayTeam": "Westchester Flames",
    "score": "2-0",
    "matchId": "5040538",
    "targetMatchId": "5042296",
    "goals": [
      "",
      "",
      "",
      "",
      "",
      "",
      "",
      ""
    ],
    "isReference": true
  },
  {
    "date": "07/06/26",
    "day": "",
    "time": "",
    "status": "FT",
    "group": "Westchester Flames Hist",
    "title": "Westchester Flames 2-4 New Jersey Copa",
    "homeTeam": "Westchester Flames",
    "awayTeam": "New Jersey Copa",
    "score": "2-4",
    "matchId": "5040446",
    "targetMatchId": "5042296",
    "goals": [
      "",
      "",
      "",
      "",
      "",
      "",
      "",
      ""
    ],
    "isReference": true
  },
  {
    "date": "01/06/26",
    "day": "",
    "time": "",
    "status": "FT",
    "group": "Westchester Flames Hist",
    "title": "Westchester Flames 1-3 Staten Island ASC",
    "homeTeam": "Westchester Flames",
    "awayTeam": "Staten Island ASC",
    "score": "1-3",
    "matchId": "5040474",
    "targetMatchId": "5042296",
    "goals": [
      "11' 0-1",
      "",
      "",
      "",
      "48' 0-2",
      "64' 0-3",
      "88' 1-3",
      ""
    ],
    "isReference": true
  },
  {
    "date": "28/05/26",
    "day": "",
    "time": "",
    "status": "FT",
    "group": "Westchester Flames Hist",
    "title": "Manhattan SC 6-2 Westchester Flames",
    "homeTeam": "Manhattan SC",
    "awayTeam": "Westchester Flames",
    "score": "6-2",
    "matchId": "5040267",
    "targetMatchId": "5042296",
    "goals": [
      "11' 0-1",
      "16' 0-2",
      "44' 1-2",
      "",
      "53' 2-2",
      "61' 3-2<br>62' 4-2",
      "80' 5-2<br>85' 6-2",
      ""
    ],
    "isReference": true
  },
  {
    "date": "22/05/26",
    "day": "",
    "time": "",
    "status": "FT",
    "group": "Westchester Flames Hist",
    "title": "FC Motown II 6-0 Westchester Flames",
    "homeTeam": "FC Motown II",
    "awayTeam": "Westchester Flames",
    "score": "6-0",
    "matchId": "5040317",
    "targetMatchId": "5042296",
    "goals": [
      "11' 1-0",
      "",
      "44' 2-0",
      "",
      "60' 3-0",
      "63' 4-0<br>68' 5-0",
      "80' 6-0",
      ""
    ],
    "isReference": true
  },
  {
    "date": "13/07/25",
    "day": "",
    "time": "",
    "status": "FT",
    "group": "Westchester Flames Hist",
    "title": "Westchester Flames 1-3 Long Island Rough Riders",
    "homeTeam": "Westchester Flames",
    "awayTeam": "Long Island Rough Riders",
    "score": "1-3",
    "matchId": "4846040",
    "targetMatchId": "5042296",
    "goals": [
      "",
      "21' 0-1",
      "",
      "",
      "50' 1-1<br>59' 1-2",
      "",
      "77' 1-3",
      ""
    ],
    "isReference": true
  },
  {
    "date": "03/07/25",
    "day": "",
    "time": "",
    "status": "FT",
    "group": "Westchester Flames Hist",
    "title": "Westchester Flames 0-1 FC Motown II",
    "homeTeam": "Westchester Flames",
    "awayTeam": "FC Motown II",
    "score": "0-1",
    "matchId": "4846039",
    "targetMatchId": "5042296",
    "goals": [
      "",
      "",
      "",
      "",
      "",
      "",
      "",
      ""
    ],
    "isReference": true
  },
  {
    "date": "29/06/25",
    "day": "",
    "time": "",
    "status": "FT",
    "group": "Westchester Flames Hist",
    "title": "Staten Island ASC 1-1 Westchester Flames",
    "homeTeam": "Staten Island ASC",
    "awayTeam": "Westchester Flames",
    "score": "1-1",
    "matchId": "4845812",
    "targetMatchId": "5042296",
    "goals": [
      "",
      "30' 1-0",
      "39' 1-1",
      "",
      "",
      "",
      "",
      ""
    ],
    "isReference": true
  },
  {
    "date": "22/06/25",
    "day": "",
    "time": "",
    "status": "FT",
    "group": "Westchester Flames Hist",
    "title": "Westchester Flames 0-2 Staten Island ASC",
    "homeTeam": "Westchester Flames",
    "awayTeam": "Staten Island ASC",
    "score": "0-2",
    "matchId": "4845719",
    "targetMatchId": "5042296",
    "goals": [
      "",
      "",
      "",
      "",
      "",
      "",
      "",
      ""
    ],
    "isReference": true
  },
  {
    "date": "19/06/25",
    "day": "",
    "time": "",
    "status": "FT",
    "group": "Westchester Flames Hist",
    "title": "Morris Elite 2-2 Westchester Flames",
    "homeTeam": "Morris Elite",
    "awayTeam": "Westchester Flames",
    "score": "2-2",
    "matchId": "4846071",
    "targetMatchId": "5042296",
    "goals": [
      "",
      "22' 0-1<br>24' 1-1",
      "",
      "",
      "",
      "62' 2-1<br>74' 2-2",
      "",
      ""
    ],
    "isReference": true
  },
  {
    "date": "15/06/25",
    "day": "",
    "time": "",
    "status": "FT",
    "group": "Westchester Flames Hist",
    "title": "Hudson Valley Hammers 1-0 Westchester Flames",
    "homeTeam": "Hudson Valley Hammers",
    "awayTeam": "Westchester Flames",
    "score": "1-0",
    "matchId": "4846068",
    "targetMatchId": "5042296",
    "goals": [
      "",
      "",
      "",
      "",
      "",
      "",
      "",
      ""
    ],
    "isReference": true
  },
  {
    "date": "12/06/25",
    "day": "",
    "time": "",
    "status": "FT",
    "group": "Westchester Flames Hist",
    "title": "Ironbound SC 0-2 Westchester Flames",
    "homeTeam": "Ironbound SC",
    "awayTeam": "Westchester Flames",
    "score": "0-2",
    "matchId": "4845552",
    "targetMatchId": "5042296",
    "goals": [
      "",
      "",
      "31' 0-1",
      "",
      "",
      "75' 0-2",
      "",
      ""
    ],
    "isReference": true
  },
  {
    "date": "09/06/25",
    "day": "",
    "time": "",
    "status": "FT",
    "group": "Westchester Flames Hist",
    "title": "Cedar Stars Rush 3-1 Westchester Flames",
    "homeTeam": "Cedar Stars Rush",
    "awayTeam": "Westchester Flames",
    "score": "3-1",
    "matchId": "4845521",
    "targetMatchId": "5042296",
    "goals": [
      "",
      "27' 1-0",
      "31' 2-0",
      "",
      "53' 2-1",
      "75' 3-1",
      "",
      ""
    ],
    "isReference": true
  },
  {
    "date": "05/06/25",
    "day": "",
    "time": "",
    "status": "FT",
    "group": "Westchester Flames Hist",
    "title": "Westchester Flames 1-3 Manhattan SC",
    "homeTeam": "Westchester Flames",
    "awayTeam": "Manhattan SC",
    "score": "1-3",
    "matchId": "4845448",
    "targetMatchId": "5042296",
    "goals": [
      "2' 0-0<br>2' 0-1",
      "",
      "35' 0-2<br>39' 1-2",
      "",
      "58' 1-3",
      "",
      "",
      ""
    ],
    "isReference": true
  },
  {
    "date": "01/06/25",
    "day": "",
    "time": "",
    "status": "FT",
    "group": "Westchester Flames Hist",
    "title": "Westchester Flames 1-1 Ironbound SC",
    "homeTeam": "Westchester Flames",
    "awayTeam": "Ironbound SC",
    "score": "1-1",
    "matchId": "4845388",
    "targetMatchId": "5042296",
    "goals": [
      "",
      "",
      "",
      "",
      "",
      "",
      "",
      ""
    ],
    "isReference": true
  }
]