[
  {
    "date": "26/06/25",
    "day": "",
    "time": "",
    "status": "FT",
    "group": "H2H",
    "title": "Caracas FC 4-0 Aragua FC",
    "homeTeam": "Caracas FC",
    "awayTeam": "Aragua FC",
    "score": "4-0",
    "matchId": "4874129",
    "targetMatchId": "5083827",
    "goals": [
      "",
      "25' 1-0",
      "42' 2-0",
      "",
      "",
      "",
      "79' 3-0<br>82' 4-0",
      ""
    ],
    "isReference": true
  },
  {
    "date": "19/06/25",
    "day": "",
    "time": "",
    "status": "FT",
    "group": "H2H",
    "title": "Aragua FC 2-1 Caracas FC",
    "homeTeam": "Aragua FC",
    "awayTeam": "Caracas FC",
    "score": "2-1",
    "matchId": "4874111",
    "targetMatchId": "5083827",
    "goals": [
      "6' 0-1",
      "",
      "",
      "",
      "",
      "70' 1-1",
      "88' 2-1",
      ""
    ],
    "isReference": true
  },
  {
    "date": "19/09/22",
    "day": "",
    "time": "",
    "status": "FT",
    "group": "H2H",
    "title": "Aragua FC 4-2 Caracas FC",
    "homeTeam": "Aragua FC",
    "awayTeam": "Caracas FC",
    "score": "4-2",
    "matchId": "4280942",
    "targetMatchId": "5083827",
    "goals": [
      "3' 0-1",
      "",
      "38' 1-1",
      "",
      "52' 2-1<br>54' 3-1",
      "63' 4-1",
      "81' 4-2",
      ""
    ],
    "isReference": true
  },
  {
    "date": "28/05/26",
    "day": "",
    "time": "",
    "status": "FT",
    "group": "Caracas FC Hist",
    "title": "Caracas FC 1-3 Botafogo de Futebol e Regatas",
    "homeTeam": "Caracas FC",
    "awayTeam": "Botafogo de Futebol e Regatas",
    "score": "1-3",
    "matchId": "5055239",
    "targetMatchId": "5083827",
    "goals": [
      "",
      "",
      "36' 1-0",
      "",
      "",
      "61' 1-1<br>72' 1-2",
      "",
      "90+2' 1-3"
    ],
    "isReference": true
  },
  {
    "date": "22/05/26",
    "day": "",
    "time": "",
    "status": "FT",
    "group": "Caracas FC Hist",
    "title": "Racing Club de Avellaneda 2-2 Caracas FC",
    "homeTeam": "Racing Club de Avellaneda",
    "awayTeam": "Caracas FC",
    "score": "2-2",
    "matchId": "5055237",
    "targetMatchId": "5083827",
    "goals": [
      "1' 0-1<br>5' 1-1",
      "",
      "37' 2-1",
      "",
      "",
      "74' 2-2",
      "",
      ""
    ],
    "isReference": true
  },
  {
    "date": "06/05/26",
    "day": "",
    "time": "",
    "status": "FT",
    "group": "Caracas FC Hist",
    "title": "Club Independiente Petrolero 2-3 Caracas FC",
    "homeTeam": "Club Independiente Petrolero",
    "awayTeam": "Caracas FC",
    "score": "2-3",
    "matchId": "5055234",
    "targetMatchId": "5083827",
    "goals": [
      "4' 0-1<br>15' 0-2",
      "",
      "",
      "",
      "55' 1-2<br>59' 2-2",
      "67' 2-3",
      "",
      ""
    ],
    "isReference": true
  },
  {
    "date": "07/06/26",
    "day": "",
    "time": "",
    "status": "FT",
    "group": "Aragua FC Hist",
    "title": "Aragua FC 1-2 Monagas B",
    "homeTeam": "Aragua FC",
    "awayTeam": "Monagas B",
    "score": "1-2",
    "matchId": "5071713",
    "targetMatchId": "5083827",
    "goals": [
      "5' 0-1",
      "",
      "",
      "",
      "",
      "69' 1-1",
      "78' 1-2",
      ""
    ],
    "isReference": true
  },
  {
    "date": "01/06/26",
    "day": "",
    "time": "",
    "status": "FT",
    "group": "Aragua FC Hist",
    "title": "Dynamo Puerto 1-2 Aragua FC",
    "homeTeam": "Dynamo Puerto",
    "awayTeam": "Aragua FC",
    "score": "1-2",
    "matchId": "5067263",
    "targetMatchId": "5083827",
    "goals": [
      "",
      "",
      "",
      "45+3' 0-1",
      "57' 0-2",
      "",
      "83' 1-2",
      ""
    ],
    "isReference": true
  },
  {
    "date": "24/05/26",
    "day": "",
    "time": "",
    "status": "FT",
    "group": "Aragua FC Hist",
    "title": "Aragua FC 2-0 Mineros de Guayana",
    "homeTeam": "Aragua FC",
    "awayTeam": "Mineros de Guayana",
    "score": "2-0",
    "matchId": "5067245",
    "targetMatchId": "5083827",
    "goals": [
      "14' 1-0",
      "18' 2-0",
      "",
      "",
      "",
      "",
      "",
      ""
    ],
    "isReference": true
  }
]