[
  {
    "date": "29/04/26",
    "day": "",
    "time": "",
    "status": "FT",
    "group": "H2H",
    "title": "FK Orenburg B 1-1 Dynamo Barnaul",
    "homeTeam": "FK Orenburg B",
    "awayTeam": "Dynamo Barnaul",
    "score": "1-1",
    "matchId": "5056367",
    "targetMatchId": "5056303",
    "goals": [
      "9' 1-0<br>13' 1-1",
      "",
      "",
      "",
      "",
      "",
      "",
      ""
    ],
    "isReference": true
  },
  {
    "date": "10/08/25",
    "day": "",
    "time": "",
    "status": "FT",
    "group": "H2H",
    "title": "Dynamo Barnaul 2-0 FK Orenburg B",
    "homeTeam": "Dynamo Barnaul",
    "awayTeam": "FK Orenburg B",
    "score": "2-0",
    "matchId": "4857735",
    "targetMatchId": "5056303",
    "goals": [
      "",
      "",
      "",
      "",
      "",
      "",
      "84' 1-0",
      "90+3' 2-0"
    ],
    "isReference": true
  },
  {
    "date": "04/05/25",
    "day": "",
    "time": "",
    "status": "FT",
    "group": "H2H",
    "title": "FK Orenburg B 1-1 Dynamo Barnaul",
    "homeTeam": "FK Orenburg B",
    "awayTeam": "Dynamo Barnaul",
    "score": "1-1",
    "matchId": "4857722",
    "targetMatchId": "5056303",
    "goals": [
      "",
      "",
      "",
      "45+1' 0-1",
      "",
      "",
      "89' 1-1",
      ""
    ],
    "isReference": true
  },
  {
    "date": "28/06/26",
    "day": "",
    "time": "",
    "status": "FT",
    "group": "Dynamo Barnaul Hist",
    "title": "Dynamo Barnaul 2-0 Rubin Kazan B",
    "homeTeam": "Dynamo Barnaul",
    "awayTeam": "Rubin Kazan B",
    "score": "2-0",
    "matchId": "5056357",
    "targetMatchId": "5056303",
    "goals": [
      "",
      "",
      "",
      "",
      "51' 1-0",
      "",
      "80' 2-0",
      ""
    ],
    "isReference": true
  },
  {
    "date": "21/06/26",
    "day": "",
    "time": "",
    "status": "FT",
    "group": "Dynamo Barnaul Hist",
    "title": "NoSta Novotroitsk 0-1 Dynamo Barnaul",
    "homeTeam": "NoSta Novotroitsk",
    "awayTeam": "Dynamo Barnaul",
    "score": "0-1",
    "matchId": "5056352",
    "targetMatchId": "5056303",
    "goals": [
      "",
      "",
      "44' 0-1",
      "",
      "",
      "",
      "",
      ""
    ],
    "isReference": true
  },
  {
    "date": "14/06/26",
    "day": "",
    "time": "",
    "status": "FT",
    "group": "Dynamo Barnaul Hist",
    "title": "Dynamo Barnaul 1-1 Krylya Sovetov Samara B",
    "homeTeam": "Dynamo Barnaul",
    "awayTeam": "Krylya Sovetov Samara B",
    "score": "1-1",
    "matchId": "5056345",
    "targetMatchId": "5056303",
    "goals": [
      "",
      "",
      "35' 0-1",
      "",
      "60' 1-1",
      "",
      "",
      ""
    ],
    "isReference": true
  },
  {
    "date": "28/06/26",
    "day": "",
    "time": "",
    "status": "FT",
    "group": "FK Orenburg B Hist",
    "title": "Akron Togliatti B 1-1 FK Orenburg B",
    "homeTeam": "Akron Togliatti B",
    "awayTeam": "FK Orenburg B",
    "score": "1-1",
    "matchId": "5056355",
    "targetMatchId": "5056303",
    "goals": [
      "",
      "",
      "",
      "",
      "52' 1-0",
      "",
      "88' 1-1",
      ""
    ],
    "isReference": true
  },
  {
    "date": "21/06/26",
    "day": "",
    "time": "",
    "status": "FT",
    "group": "FK Orenburg B Hist",
    "title": "FK Orenburg B 2-4 Pobeda Nizhniy Novgorod",
    "homeTeam": "FK Orenburg B",
    "awayTeam": "Pobeda Nizhniy Novgorod",
    "score": "2-4",
    "matchId": "5056353",
    "targetMatchId": "5056303",
    "goals": [
      "5' 0-1",
      "27' 0-2",
      "33' 1-2<br>40' 2-2",
      "",
      "51' 2-3",
      "",
      "",
      "90+4' 2-4"
    ],
    "isReference": true
  },
  {
    "date": "14/06/26",
    "day": "",
    "time": "",
    "status": "FT",
    "group": "FK Orenburg B Hist",
    "title": "FK Ural B 5-0 FK Orenburg B",
    "homeTeam": "FK Ural B",
    "awayTeam": "FK Orenburg B",
    "score": "5-0",
    "matchId": "5056348",
    "targetMatchId": "5056303",
    "goals": [
      "12' 1-0",
      "24' 2-0",
      "",
      "",
      "49' 3-0<br>58' 4-0",
      "",
      "81' 5-0",
      ""
    ],
    "isReference": true
  }
]