[
  {
    "date": "",
    "day": "",
    "time": "",
    "status": "FT",
    "group": "H2H",
    "title": " - ",
    "homeTeam": "",
    "awayTeam": "",
    "score": "-",
    "matchId": "",
    "targetMatchId": "5114331",
    "goals": [
      "",
      "",
      "",
      "",
      "",
      "",
      "",
      ""
    ],
    "isReference": true
  },
  {
    "date": "17/06/26",
    "day": "",
    "time": "",
    "status": "FT",
    "group": "Connecticut Legends Women\\s Hist",
    "title": "Connecticut Legends Women's 2-1 Worcester Wanderers Women's",
    "homeTeam": "Connecticut Legends Women's",
    "awayTeam": "Worcester Wanderers Women's",
    "score": "2-1",
    "matchId": "5078390",
    "targetMatchId": "5114331",
    "goals": [
      "",
      "",
      "",
      "",
      "",
      "",
      "",
      ""
    ],
    "isReference": true
  },
  {
    "date": "28/06/26",
    "day": "",
    "time": "",
    "status": "FT",
    "group": "New England Mutiny Women\\s Hist",
    "title": "New England Mutiny Women's 0-3 Vermont Green Women's",
    "homeTeam": "New England Mutiny Women's",
    "awayTeam": "Vermont Green Women's",
    "score": "0-3",
    "matchId": "5093298",
    "targetMatchId": "5114331",
    "goals": [
      "",
      "",
      "",
      "",
      "",
      "",
      "",
      ""
    ],
    "isReference": true
  },
  {
    "date": "21/06/26",
    "day": "",
    "time": "",
    "status": "FT",
    "group": "New England Mutiny Women\\s Hist",
    "title": "New England Mutiny Women's 2-4 Hudson Valley Crusaders Women's",
    "homeTeam": "New England Mutiny Women's",
    "awayTeam": "Hudson Valley Crusaders Women's",
    "score": "2-4",
    "matchId": "5080393",
    "targetMatchId": "5114331",
    "goals": [
      "",
      "",
      "",
      "",
      "",
      "",
      "",
      ""
    ],
    "isReference": true
  },
  {
    "date": "10/06/26",
    "day": "",
    "time": "",
    "status": "FT",
    "group": "New England Mutiny Women\\s Hist",
    "title": "Hudson Valley Crusaders Women's 2-1 New England Mutiny Women's",
    "homeTeam": "Hudson Valley Crusaders Women's",
    "awayTeam": "New England Mutiny Women's",
    "score": "2-1",
    "matchId": "5073323",
    "targetMatchId": "5114331",
    "goals": [
      "",
      "30' 1-0",
      "",
      "",
      "53' 1-1<br>60' 2-1",
      "",
      "",
      ""
    ],
    "isReference": true
  },
  {
    "date": "27/05/26",
    "day": "",
    "time": "",
    "status": "FT",
    "group": "New England Mutiny Women\\s Hist",
    "title": "New England Mutiny Women's 1-1 Vermont Green Women's",
    "homeTeam": "New England Mutiny Women's",
    "awayTeam": "Vermont Green Women's",
    "score": "1-1",
    "matchId": "5069617",
    "targetMatchId": "5114331",
    "goals": [
      "",
      "",
      "",
      "",
      "",
      "",
      "",
      ""
    ],
    "isReference": true
  },
  {
    "date": "15/07/24",
    "day": "",
    "time": "",
    "status": "FT",
    "group": "New England Mutiny Women\\s Hist",
    "title": "New England Mutiny Women's 0-0 Sporting CT Women's",
    "homeTeam": "New England Mutiny Women's",
    "awayTeam": "Sporting CT Women's",
    "score": "0-0",
    "matchId": "4732728",
    "targetMatchId": "5114331",
    "goals": [
      "",
      "",
      "",
      "",
      "",
      "",
      "",
      ""
    ],
    "isReference": true
  },
  {
    "date": "13/07/24",
    "day": "",
    "time": "",
    "status": "FT",
    "group": "New England Mutiny Women\\s Hist",
    "title": "New England Mutiny Women's 2-1 Pittsburgh Steel City Women's",
    "homeTeam": "New England Mutiny Women's",
    "awayTeam": "Pittsburgh Steel City Women's",
    "score": "2-1",
    "matchId": "4730686",
    "targetMatchId": "5114331",
    "goals": [
      "",
      "",
      "",
      "",
      "",
      "",
      "",
      ""
    ],
    "isReference": true
  },
  {
    "date": "30/06/24",
    "day": "",
    "time": "",
    "status": "FT",
    "group": "New England Mutiny Women\\s Hist",
    "title": "New England Mutiny Women's 5-0 Connecticut Rush Women's",
    "homeTeam": "New England Mutiny Women's",
    "awayTeam": "Connecticut Rush Women's",
    "score": "5-0",
    "matchId": "4714644",
    "targetMatchId": "5114331",
    "goals": [
      "",
      "",
      "",
      "",
      "",
      "",
      "",
      ""
    ],
    "isReference": true
  },
  {
    "date": "26/06/24",
    "day": "",
    "time": "",
    "status": "FT",
    "group": "New England Mutiny Women\\s Hist",
    "title": "Connecticut Rush Women's 0-4 New England Mutiny Women's",
    "homeTeam": "Connecticut Rush Women's",
    "awayTeam": "New England Mutiny Women's",
    "score": "0-4",
    "matchId": "4706501",
    "targetMatchId": "5114331",
    "goals": [
      "",
      "",
      "",
      "",
      "",
      "",
      "",
      ""
    ],
    "isReference": true
  },
  {
    "date": "09/06/24",
    "day": "",
    "time": "",
    "status": "FT",
    "group": "New England Mutiny Women\\s Hist",
    "title": "Maine Footy Women's 0-1 New England Mutiny Women's",
    "homeTeam": "Maine Footy Women's",
    "awayTeam": "New England Mutiny Women's",
    "score": "0-1",
    "matchId": "4699113",
    "targetMatchId": "5114331",
    "goals": [
      "",
      "",
      "",
      "",
      "",
      "",
      "",
      ""
    ],
    "isReference": true
  },
  {
    "date": "02/06/24",
    "day": "",
    "time": "",
    "status": "FT",
    "group": "New England Mutiny Women\\s Hist",
    "title": "New England Mutiny Women's 7-1 Albany Rush Women's",
    "homeTeam": "New England Mutiny Women's",
    "awayTeam": "Albany Rush Women's",
    "score": "7-1",
    "matchId": "4697956",
    "targetMatchId": "5114331",
    "goals": [
      "",
      "",
      "",
      "",
      "",
      "",
      "",
      ""
    ],
    "isReference": true
  },
  {
    "date": "25/05/24",
    "day": "",
    "time": "",
    "status": "FT",
    "group": "New England Mutiny Women\\s Hist",
    "title": "New England Mutiny Women's 4-1 Sporting CT Women's",
    "homeTeam": "New England Mutiny Women's",
    "awayTeam": "Sporting CT Women's",
    "score": "4-1",
    "matchId": "4696866",
    "targetMatchId": "5114331",
    "goals": [
      "",
      "",
      "",
      "",
      "",
      "",
      "",
      ""
    ],
    "isReference": true
  },
  {
    "date": "13/06/23",
    "day": "",
    "time": "",
    "status": "FT",
    "group": "New England Mutiny Women\\s Hist",
    "title": "Scorpions SC Women's 0-3 New England Mutiny Women's",
    "homeTeam": "Scorpions SC Women's",
    "awayTeam": "New England Mutiny Women's",
    "score": "0-3",
    "matchId": "4494728",
    "targetMatchId": "5114331",
    "goals": [
      "",
      "",
      "",
      "",
      "",
      "",
      "",
      ""
    ],
    "isReference": true
  },
  {
    "date": "07/07/22",
    "day": "",
    "time": "",
    "status": "FT",
    "group": "New England Mutiny Women\\s Hist",
    "title": "Connecticut Rush Women's 1-2 New England Mutiny Women's",
    "homeTeam": "Connecticut Rush Women's",
    "awayTeam": "New England Mutiny Women's",
    "score": "1-2",
    "matchId": "4337832",
    "targetMatchId": "5114331",
    "goals": [
      "",
      "",
      "",
      "",
      "",
      "",
      "",
      ""
    ],
    "isReference": true
  },
  {
    "date": "12/06/22",
    "day": "",
    "time": "",
    "status": "FT",
    "group": "New England Mutiny Women\\s Hist",
    "title": "New England Mutiny Women's 2-0 Connecticut Fusion Women's",
    "homeTeam": "New England Mutiny Women's",
    "awayTeam": "Connecticut Fusion Women's",
    "score": "2-0",
    "matchId": "4318079",
    "targetMatchId": "5114331",
    "goals": [
      "",
      "",
      "",
      "",
      "",
      "",
      "",
      ""
    ],
    "isReference": true
  },
  {
    "date": "27/05/22",
    "day": "",
    "time": "",
    "status": "FT",
    "group": "New England Mutiny Women\\s Hist",
    "title": "Connecticut Fusion Women's 1-2 New England Mutiny Women's",
    "homeTeam": "Connecticut Fusion Women's",
    "awayTeam": "New England Mutiny Women's",
    "score": "1-2",
    "matchId": "4314652",
    "targetMatchId": "5114331",
    "goals": [
      "",
      "",
      "",
      "",
      "",
      "",
      "",
      ""
    ],
    "isReference": true
  },
  {
    "date": "15/05/22",
    "day": "",
    "time": "",
    "status": "FT",
    "group": "New England Mutiny Women\\s Hist",
    "title": "New England Mutiny Women's 1-0 Scorpions SC Women's",
    "homeTeam": "New England Mutiny Women's",
    "awayTeam": "Scorpions SC Women's",
    "score": "1-0",
    "matchId": "4312503",
    "targetMatchId": "5114331",
    "goals": [
      "",
      "",
      "",
      "",
      "",
      "",
      "",
      ""
    ],
    "isReference": true
  },
  {
    "date": "13/07/21",
    "day": "",
    "time": "",
    "status": "FT",
    "group": "New England Mutiny Women\\s Hist",
    "title": "Connecticut Rush Women's 0-1 New England Mutiny Women's",
    "homeTeam": "Connecticut Rush Women's",
    "awayTeam": "New England Mutiny Women's",
    "score": "0-1",
    "matchId": "4174250",
    "targetMatchId": "5114331",
    "goals": [
      "",
      "",
      "",
      "",
      "",
      "",
      "",
      ""
    ],
    "isReference": true
  },
  {
    "date": "15/07/19",
    "day": "",
    "time": "",
    "status": "FT",
    "group": "New England Mutiny Women\\s Hist",
    "title": "New England Mutiny Women's 1-2 Lancaster Inferno Women's",
    "homeTeam": "New England Mutiny Women's",
    "awayTeam": "Lancaster Inferno Women's",
    "score": "1-2",
    "matchId": "3919136",
    "targetMatchId": "5114331",
    "goals": [
      "",
      "",
      "",
      "",
      "",
      "",
      "",
      ""
    ],
    "isReference": true
  },
  {
    "date": "13/07/19",
    "day": "",
    "time": "",
    "status": "FT",
    "group": "New England Mutiny Women\\s Hist",
    "title": "New England Mutiny Women's 3-0 Long Island Rough Riders Women's",
    "homeTeam": "New England Mutiny Women's",
    "awayTeam": "Long Island Rough Riders Women's",
    "score": "3-0",
    "matchId": "3918192",
    "targetMatchId": "5114331",
    "goals": [
      "",
      "17' 1-0",
      "",
      "",
      "48' 2-0",
      "",
      "90' 3-0",
      ""
    ],
    "isReference": true
  }
]