[
  {
    "date": "",
    "day": "",
    "time": "",
    "status": "FT",
    "group": "H2H",
    "title": " - ",
    "homeTeam": "",
    "awayTeam": "",
    "score": "-",
    "matchId": "",
    "targetMatchId": "5114542",
    "goals": [
      "",
      "",
      "",
      "",
      "",
      "",
      "",
      ""
    ],
    "isReference": true
  },
  {
    "date": "10/07/26",
    "day": "",
    "time": "",
    "status": "FT",
    "group": "CA Penarol Women\\s Hist",
    "title": "CR Flamengo (RJ) Women's 4-1 CA Penarol Women's",
    "homeTeam": "CR Flamengo (RJ) Women's",
    "awayTeam": "CA Penarol Women's",
    "score": "4-1",
    "matchId": "5112587",
    "targetMatchId": "5114542",
    "goals": [
      "",
      "",
      "",
      "",
      "",
      "",
      "",
      ""
    ],
    "isReference": true
  },
  {
    "date": "20/10/25",
    "day": "",
    "time": "",
    "status": "FT",
    "group": "CA Penarol Women\\s Hist",
    "title": "CA Penarol Women's 1-1 Gimnasia La Plata Women's",
    "homeTeam": "CA Penarol Women's",
    "awayTeam": "Gimnasia La Plata Women's",
    "score": "1-1",
    "matchId": "4992661",
    "targetMatchId": "5114542",
    "goals": [
      "",
      "20' 0-1",
      "",
      "",
      "",
      "",
      "82' 1-1",
      ""
    ],
    "isReference": true
  },
  {
    "date": "17/10/25",
    "day": "",
    "time": "",
    "status": "FT",
    "group": "CA Penarol Women\\s Hist",
    "title": "Gremio Women's 2-0 CA Penarol Women's",
    "homeTeam": "Gremio Women's",
    "awayTeam": "CA Penarol Women's",
    "score": "2-0",
    "matchId": "4992455",
    "targetMatchId": "5114542",
    "goals": [
      "",
      "",
      "",
      "",
      "",
      "",
      "",
      ""
    ],
    "isReference": true
  },
  {
    "date": "11/10/24",
    "day": "",
    "time": "",
    "status": "FT",
    "group": "CA Penarol Women\\s Hist",
    "title": "Independiente Del Valle Women's 2-0 CA Penarol Women's",
    "homeTeam": "Independiente Del Valle Women's",
    "awayTeam": "CA Penarol Women's",
    "score": "2-0",
    "matchId": "4795164",
    "targetMatchId": "5114542",
    "goals": [
      "",
      "",
      "",
      "",
      "51' 1-0<br>53' 2-0",
      "",
      "",
      ""
    ],
    "isReference": true
  },
  {
    "date": "08/10/24",
    "day": "",
    "time": "",
    "status": "FT",
    "group": "CA Penarol Women\\s Hist",
    "title": "Ferroviaria SP Women's 2-2 CA Penarol Women's",
    "homeTeam": "Ferroviaria SP Women's",
    "awayTeam": "CA Penarol Women's",
    "score": "2-2",
    "matchId": "4795161",
    "targetMatchId": "5114542",
    "goals": [
      "",
      "28' 1-0",
      "42' 1-1",
      "",
      "",
      "",
      "78' 2-1<br>81' 2-2",
      ""
    ],
    "isReference": true
  },
  {
    "date": "05/10/24",
    "day": "",
    "time": "",
    "status": "FT",
    "group": "CA Penarol Women\\s Hist",
    "title": "CA Penarol Women's 0-0 Independiente Santa Fe Women's",
    "homeTeam": "CA Penarol Women's",
    "awayTeam": "Independiente Santa Fe Women's",
    "score": "0-0",
    "matchId": "4795160",
    "targetMatchId": "5114542",
    "goals": [
      "",
      "",
      "",
      "",
      "",
      "",
      "",
      ""
    ],
    "isReference": true
  },
  {
    "date": "13/03/21",
    "day": "",
    "time": "",
    "status": "FT",
    "group": "CA Penarol Women\\s Hist",
    "title": "Sportivo Limpeno Women's 0-0 CA Penarol Women's",
    "homeTeam": "Sportivo Limpeno Women's",
    "awayTeam": "CA Penarol Women's",
    "score": "0-0",
    "matchId": "4129988",
    "targetMatchId": "5114542",
    "goals": [
      "",
      "",
      "",
      "",
      "",
      "",
      "",
      ""
    ],
    "isReference": true
  },
  {
    "date": "10/03/21",
    "day": "",
    "time": "",
    "status": "FT",
    "group": "CA Penarol Women\\s Hist",
    "title": "Ferroviaria SP Women's 1-1 CA Penarol Women's",
    "homeTeam": "Ferroviaria SP Women's",
    "awayTeam": "CA Penarol Women's",
    "score": "1-1",
    "matchId": "4129984",
    "targetMatchId": "5114542",
    "goals": [
      "",
      "",
      "",
      "",
      "59' 0-1",
      "74' 1-1",
      "",
      ""
    ],
    "isReference": true
  },
  {
    "date": "07/03/21",
    "day": "",
    "time": "",
    "status": "FT",
    "group": "CA Penarol Women\\s Hist",
    "title": "CA Penarol Women's 0-1 Universidad de Chile Women's",
    "homeTeam": "CA Penarol Women's",
    "awayTeam": "Universidad de Chile Women's",
    "score": "0-1",
    "matchId": "4129964",
    "targetMatchId": "5114542",
    "goals": [
      "",
      "",
      "",
      "",
      "",
      "",
      "89' 0-1",
      ""
    ],
    "isReference": true
  },
  {
    "date": "19/10/19",
    "day": "",
    "time": "",
    "status": "FT",
    "group": "CA Penarol Women\\s Hist",
    "title": "CA Penarol Women's 0-1 Cerro Porteno Women's",
    "homeTeam": "CA Penarol Women's",
    "awayTeam": "Cerro Porteno Women's",
    "score": "0-1",
    "matchId": "3978752",
    "targetMatchId": "5114542",
    "goals": [
      "",
      "",
      "",
      "",
      "",
      "",
      "85' 0-1",
      ""
    ],
    "isReference": true
  },
  {
    "date": "16/10/19",
    "day": "",
    "time": "",
    "status": "FT",
    "group": "CA Penarol Women\\s Hist",
    "title": "CA Penarol Women's 2-2 Colo Colo Women's",
    "homeTeam": "CA Penarol Women's",
    "awayTeam": "Colo Colo Women's",
    "score": "2-2",
    "matchId": "3978750",
    "targetMatchId": "5114542",
    "goals": [
      "",
      "",
      "",
      "",
      "54' 0-1",
      "69' 1-1",
      "76' 2-1<br>83' 2-2",
      ""
    ],
    "isReference": true
  },
  {
    "date": "12/10/19",
    "day": "",
    "time": "",
    "status": "FT",
    "group": "CA Penarol Women\\s Hist",
    "title": "Atletico Huila Women's 2-1 CA Penarol Women's",
    "homeTeam": "Atletico Huila Women's",
    "awayTeam": "CA Penarol Women's",
    "score": "2-1",
    "matchId": "3978747",
    "targetMatchId": "5114542",
    "goals": [
      "",
      "28' 0-1",
      "39' 1-1<br>41' 2-1",
      "",
      "",
      "",
      "",
      ""
    ],
    "isReference": true
  },
  {
    "date": "26/11/18",
    "day": "",
    "time": "",
    "status": "FT",
    "group": "CA Penarol Women\\s Hist",
    "title": "CA Penarol Women's 0-4 Osasco Audax Women's",
    "homeTeam": "CA Penarol Women's",
    "awayTeam": "Osasco Audax Women's",
    "score": "0-4",
    "matchId": "3831471",
    "targetMatchId": "5114542",
    "goals": [
      "",
      "",
      "37' 0-1<br>38' 0-2<br>45' 0-3",
      "",
      "",
      "",
      "85' 0-4",
      ""
    ],
    "isReference": true
  },
  {
    "date": "23/11/18",
    "day": "",
    "time": "",
    "status": "FT",
    "group": "CA Penarol Women\\s Hist",
    "title": "Union Espanola Guayaquil Women's 0-2 CA Penarol Women's",
    "homeTeam": "Union Espanola Guayaquil Women's",
    "awayTeam": "CA Penarol Women's",
    "score": "0-2",
    "matchId": "3831466",
    "targetMatchId": "5114542",
    "goals": [
      "",
      "29' 0-1",
      "",
      "",
      "",
      "",
      "90' 0-2",
      ""
    ],
    "isReference": true
  },
  {
    "date": "20/11/18",
    "day": "",
    "time": "",
    "status": "FT",
    "group": "CA Penarol Women\\s Hist",
    "title": "Atletico Huila Women's 3-0 CA Penarol Women's",
    "homeTeam": "Atletico Huila Women's",
    "awayTeam": "CA Penarol Women's",
    "score": "3-0",
    "matchId": "3831372",
    "targetMatchId": "5114542",
    "goals": [
      "5' 1-0",
      "",
      "",
      "",
      "",
      "69' 2-0",
      "84' 3-0",
      ""
    ],
    "isReference": true
  },
  {
    "date": "10/07/26",
    "day": "",
    "time": "",
    "status": "FT",
    "group": "Paraguay Women\\s Hist",
    "title": "Palmeiras SP Women's 3-0 Paraguay Women's",
    "homeTeam": "Palmeiras SP Women's",
    "awayTeam": "Paraguay Women's",
    "score": "3-0",
    "matchId": "5112580",
    "targetMatchId": "5114542",
    "goals": [
      "",
      "29' 1-0",
      "38' 2-0",
      "",
      "47' 3-0",
      "",
      "",
      ""
    ],
    "isReference": true
  },
  {
    "date": "10/06/26",
    "day": "",
    "time": "",
    "status": "FT",
    "group": "Paraguay Women\\s Hist",
    "title": "Paraguay Women's 3-4 Colombia Women's",
    "homeTeam": "Paraguay Women's",
    "awayTeam": "Colombia Women's",
    "score": "3-4",
    "matchId": "4992735",
    "targetMatchId": "5114542",
    "goals": [
      "3' 1-0<br>7' 1-1<br>9' 2-1",
      "",
      "43' 2-2",
      "45+1' 3-2",
      "60' 3-3",
      "",
      "89' 3-4",
      ""
    ],
    "isReference": true
  },
  {
    "date": "06/06/26",
    "day": "",
    "time": "",
    "status": "FT",
    "group": "Paraguay Women\\s Hist",
    "title": "Bolivia Women's 0-8 Paraguay Women's",
    "homeTeam": "Bolivia Women's",
    "awayTeam": "Paraguay Women's",
    "score": "0-8",
    "matchId": "4992731",
    "targetMatchId": "5114542",
    "goals": [
      "",
      "19' 0-1<br>23' 0-2",
      "",
      "45+1' 0-3",
      "48' 0-4<br>51' 0-5<br>52' 0-6<br>58' 0-7",
      "73' 0-8",
      "",
      ""
    ],
    "isReference": true
  },
  {
    "date": "15/04/26",
    "day": "",
    "time": "",
    "status": "FT",
    "group": "Paraguay Women\\s Hist",
    "title": "Peru Women's 1-1 Paraguay Women's",
    "homeTeam": "Peru Women's",
    "awayTeam": "Paraguay Women's",
    "score": "1-1",
    "matchId": "4992723",
    "targetMatchId": "5114542",
    "goals": [
      "",
      "18' 0-1",
      "",
      "",
      "51' 1-1",
      "",
      "",
      ""
    ],
    "isReference": true
  },
  {
    "date": "11/04/26",
    "day": "",
    "time": "",
    "status": "FT",
    "group": "Paraguay Women\\s Hist",
    "title": "Paraguay Women's 2-0 Ecuador Women's",
    "homeTeam": "Paraguay Women's",
    "awayTeam": "Ecuador Women's",
    "score": "2-0",
    "matchId": "4992719",
    "targetMatchId": "5114542",
    "goals": [
      "",
      "",
      "32' 1-0",
      "",
      "",
      "",
      "",
      "90+8' 2-0"
    ],
    "isReference": true
  },
  {
    "date": "08/03/26",
    "day": "",
    "time": "",
    "status": "FT",
    "group": "Paraguay Women\\s Hist",
    "title": "Paraguay Women's 0-1 Chile Women's",
    "homeTeam": "Paraguay Women's",
    "awayTeam": "Chile Women's",
    "score": "0-1",
    "matchId": "5048895",
    "targetMatchId": "5114542",
    "goals": [
      "",
      "",
      "",
      "",
      "56' 0-1",
      "",
      "",
      ""
    ],
    "isReference": true
  },
  {
    "date": "05/03/26",
    "day": "",
    "time": "",
    "status": "FT",
    "group": "Paraguay Women\\s Hist",
    "title": "Paraguay Women's 0-1 Chile Women's",
    "homeTeam": "Paraguay Women's",
    "awayTeam": "Chile Women's",
    "score": "0-1",
    "matchId": "5047296",
    "targetMatchId": "5114542",
    "goals": [
      "",
      "",
      "",
      "",
      "",
      "",
      "77' 0-1",
      ""
    ],
    "isReference": true
  },
  {
    "date": "25/01/26",
    "day": "",
    "time": "",
    "status": "FT",
    "group": "Paraguay Women\\s Hist",
    "title": "USA Women's 6-0 Paraguay Women's",
    "homeTeam": "USA Women's",
    "awayTeam": "Paraguay Women's",
    "score": "6-0",
    "matchId": "5027529",
    "targetMatchId": "5114542",
    "goals": [
      "",
      "",
      "",
      "45+3' 1-0",
      "47' 2-0<br>53' 3-0<br>56' 4-0<br>57' 5-0",
      "72' 6-0",
      "",
      ""
    ],
    "isReference": true
  },
  {
    "date": "03/12/25",
    "day": "",
    "time": "",
    "status": "FT",
    "group": "Paraguay Women\\s Hist",
    "title": "Chile Women's 1-0 Paraguay Women's",
    "homeTeam": "Chile Women's",
    "awayTeam": "Paraguay Women's",
    "score": "1-0",
    "matchId": "4992714",
    "targetMatchId": "5114542",
    "goals": [
      "",
      "",
      "33' 1-0",
      "",
      "",
      "",
      "",
      ""
    ],
    "isReference": true
  },
  {
    "date": "29/11/25",
    "day": "",
    "time": "",
    "status": "FT",
    "group": "Paraguay Women\\s Hist",
    "title": "Paraguay Women's 1-0 Uruguay Women's",
    "homeTeam": "Paraguay Women's",
    "awayTeam": "Uruguay Women's",
    "score": "1-0",
    "matchId": "4992711",
    "targetMatchId": "5114542",
    "goals": [
      "",
      "",
      "",
      "",
      "",
      "",
      "",
      "90+6' 1-0"
    ],
    "isReference": true
  },
  {
    "date": "29/10/25",
    "day": "",
    "time": "",
    "status": "FT",
    "group": "Paraguay Women\\s Hist",
    "title": "Paraguay Women's 1-2 Venezuela Women's",
    "homeTeam": "Paraguay Women's",
    "awayTeam": "Venezuela Women's",
    "score": "1-2",
    "matchId": "4992708",
    "targetMatchId": "5114542",
    "goals": [
      "",
      "20' 0-1",
      "38' 1-1",
      "",
      "",
      "69' 1-2",
      "",
      ""
    ],
    "isReference": true
  },
  {
    "date": "25/10/25",
    "day": "",
    "time": "",
    "status": "FT",
    "group": "Paraguay Women\\s Hist",
    "title": "Argentina Women's 3-1 Paraguay Women's",
    "homeTeam": "Argentina Women's",
    "awayTeam": "Paraguay Women's",
    "score": "3-1",
    "matchId": "4992703",
    "targetMatchId": "5114542",
    "goals": [
      "",
      "17' 1-0<br>22' 2-0",
      "",
      "45+2' 2-1<br>45+3' 3-1",
      "",
      "",
      "",
      ""
    ],
    "isReference": true
  },
  {
    "date": "29/07/25",
    "day": "",
    "time": "",
    "status": "FT",
    "group": "Paraguay Women\\s Hist",
    "title": "Chile Women's 0-1 Paraguay Women's",
    "homeTeam": "Chile Women's",
    "awayTeam": "Paraguay Women's",
    "score": "0-1",
    "matchId": "4932219",
    "targetMatchId": "5114542",
    "goals": [
      "",
      "",
      "",
      "",
      "",
      "",
      "",
      "90+2' 0-1"
    ],
    "isReference": true
  },
  {
    "date": "26/07/25",
    "day": "",
    "time": "",
    "status": "FT",
    "group": "Paraguay Women\\s Hist",
    "title": "Paraguay Women's 2-1 Venezuela Women's",
    "homeTeam": "Paraguay Women's",
    "awayTeam": "Venezuela Women's",
    "score": "2-1",
    "matchId": "4908089",
    "targetMatchId": "5114542",
    "goals": [
      "",
      "",
      "40' 0-1",
      "",
      "",
      "65' 1-1",
      "85' 2-1",
      ""
    ],
    "isReference": true
  },
  {
    "date": "23/07/25",
    "day": "",
    "time": "",
    "status": "FT",
    "group": "Paraguay Women\\s Hist",
    "title": "Paraguay Women's 1-4 Brazil Women's",
    "homeTeam": "Paraguay Women's",
    "awayTeam": "Brazil Women's",
    "score": "1-4",
    "matchId": "4908085",
    "targetMatchId": "5114542",
    "goals": [
      "",
      "27' 0-1",
      "39' 0-2",
      "",
      "60' 0-3",
      "65' 1-3<br>75' 1-4",
      "",
      ""
    ],
    "isReference": true
  },
  {
    "date": "20/07/25",
    "day": "",
    "time": "",
    "status": "FT",
    "group": "Paraguay Women\\s Hist",
    "title": "Colombia Women's 4-1 Paraguay Women's",
    "homeTeam": "Colombia Women's",
    "awayTeam": "Paraguay Women's",
    "score": "4-1",
    "matchId": "4908081",
    "targetMatchId": "5114542",
    "goals": [
      "13' 1-0<br>15' 1-1",
      "",
      "",
      "",
      "57' 2-1",
      "",
      "83' 3-1",
      "90+4' 4-1"
    ],
    "isReference": true
  },
  {
    "date": "14/07/25",
    "day": "",
    "time": "",
    "status": "FT",
    "group": "Paraguay Women\\s Hist",
    "title": "Bolivia Women's 0-4 Paraguay Women's",
    "homeTeam": "Bolivia Women's",
    "awayTeam": "Paraguay Women's",
    "score": "0-4",
    "matchId": "4908070",
    "targetMatchId": "5114542",
    "goals": [
      "",
      "23' 0-1",
      "40' 0-2",
      "",
      "",
      "61' 0-3",
      "",
      "90+3' 0-4"
    ],
    "isReference": true
  },
  {
    "date": "03/06/25",
    "day": "",
    "time": "",
    "status": "FT",
    "group": "Paraguay Women\\s Hist",
    "title": "Paraguay Women's 2-0 Ecuador Women's",
    "homeTeam": "Paraguay Women's",
    "awayTeam": "Ecuador Women's",
    "score": "2-0",
    "matchId": "4872642",
    "targetMatchId": "5114542",
    "goals": [
      "2' 1-0",
      "",
      "",
      "",
      "",
      "61' 2-0",
      "",
      ""
    ],
    "isReference": true
  },
  {
    "date": "31/05/25",
    "day": "",
    "time": "",
    "status": "FT",
    "group": "Paraguay Women\\s Hist",
    "title": "Paraguay Women's 0-0 Ecuador Women's",
    "homeTeam": "Paraguay Women's",
    "awayTeam": "Ecuador Women's",
    "score": "0-0",
    "matchId": "4872633",
    "targetMatchId": "5114542",
    "goals": [
      "",
      "",
      "",
      "",
      "",
      "",
      "",
      ""
    ],
    "isReference": true
  },
  {
    "date": "25/02/25",
    "day": "",
    "time": "",
    "status": "FT",
    "group": "Paraguay Women\\s Hist",
    "title": "Paraguay Women's 0-1 Uruguay Women's",
    "homeTeam": "Paraguay Women's",
    "awayTeam": "Uruguay Women's",
    "score": "0-1",
    "matchId": "4847598",
    "targetMatchId": "5114542",
    "goals": [
      "",
      "",
      "",
      "",
      "57' 0-1",
      "61' 0-1",
      "",
      ""
    ],
    "isReference": true
  }
]